everytime_parser/__init__.py
everytime_parser/everytime.py
everytime_parser/util.py
everytime_parser/examples/__init__.py
everytime_parser/examples/auth.py
everytime_parser/examples/get_friend_list.py
everytime_parser/examples/send_friend.py
everytime_parser-0.1.6.dist-info/METADATA
everytime_parser-0.1.6.dist-info/WHEEL
everytime_parser-0.1.6.dist-info/top_level.txt
everytime_parser-0.1.6.dist-info/RECORD
