Metadata-Version: 2.1
Name: everytime-parser
Version: 0.1.6
Summary: everytime_parser and it serve some utility
Home-page: https://github.com/zaeval/everytime_parser
Author: zaeval
Author-email: zaeval@among.software
License: UNKNOWN
Platform: UNKNOWN
Classifier: Programming Language :: Python :: 3
Classifier: License :: OSI Approved :: MIT License
Classifier: Operating System :: OS Independent
Requires-Dist: requests
Requires-Dist: bs4
